{
  "AED": "Araabia Ühendemiraadid Dirham",
  "AFN": "Afganistani afgaan",
  "ALL": "Albaania leek",
  "AMD": "Armeenia draam",
  "ANG": "Hollandi Antillide kulden",
  "AOA": "Angoolan kwanza",
  "ARS": "Argentiina peeso",
  "AUD": "Austraalia dollar",
  "AWG": "Aruba Florin",
  "AZN": "Aserbaidžaani manat",
  "BAM": "Bosnia ja Hertsegoviina kabriolettmärk",
  "BBD": "Barbadose dollar",
  "BDT": "Bangladeshi taka",
  "BGN": "Bulgaaria Lev",
  "BHD": "Bahreini dinaar",
  "BIF": "Burundi frank",
  "BMD": "Bermudani dollar",
  "BND": "Brunei dollar",
  "BOB": "Boliivia Boliviano",
  "BRL": "Brasiilia Real",
  "BSD": "Bahama dollar",
  "BTC": "Bitcoin",
  "BTN": "Bhutani Ngultrum",
  "BWP": "Botswanan Pula",
  "BYN": "Valgevene rubla",
  "BZD": "Belize'i dollar",
  "CAD": "Kanada dollar",
  "CDF": "Kongo frank",
  "CHF": "Šveitsi frank",
  "CLF": "Tšiili arveldusühik (UF)",
  "CLP": "Tšiili peeso",
  "CNY": "Hiina jüaan",
  "COP": "Colombia peeso",
  "CRC": "Costa Rica Colón",
  "CUC": "Kuuba konverteeritav peeso",
  "CUP": "Kuuba peeso",
  "CVE": "Cabo Verde eskuudo",
  "CZK": "Tšehhi Vabariik Koruna",
  "DJF": "Djibouti frank",
  "DKK": "Taani kroon",
  "DOP": "Dominikaani peeso",
  "DZD": "Alžeeria dinaar",
  "EGP": "Egiptuse nael",
  "ERN": "Eritrea Nakfa",
  "ETB": "Etioopia Birr",
  "EUR": "Euro",
  "FJD": "Fidži dollar",
  "FKP": "Falklandi saarte nael",
  "GBP": "Suurbritannia naelsterling",
  "GEL": "Georgi Lari",
  "GGP": "Guernsey nael",
  "GHS": "Ghana Cedi",
  "GIP": "Gibraltari nael",
  "GMD": "Gambia Dalasi",
  "GNF": "Guinea frank",
  "GTQ": "Guatemala Quetzal",
  "GYD": "Guajaana dollar",
  "HKD": "Hongkongi dollar",
  "HNL": "Hondurase Lempira",
  "HRK": "Horvaatia kuna",
  "HTG": "Haiti Gourde",
  "HUF": "Ungari forint",
  "IDR": "Indoneesia ruupia",
  "ILS": "Iisraeli uus shekel",
  "IMP": "Manxi nael",
  "INR": "India ruupia",
  "IQD": "Iraagi dinaar",
  "IRR": "Iraani riaal",
  "ISK": "Islandi kroon",
  "JEP": "Jersey nael",
  "JMD": "Jamaica dollar",
  "JOD": "Jordaania dinaar",
  "JPY": "Jaapani jeen",
  "KES": "Keenia šilling",
  "KGS": "Kõrgõstani Som",
  "KHR": "Kambodža Riel",
  "KMF": "Komooride frank",
  "KPW": "Põhja-Korea võit",
  "KRW": "Lõuna-Korea võit",
  "KWD": "Kuveidi dinaar",
  "KYD": "Kaimanisaarte dollar",
  "KZT": "Kasahstani Tenge",
  "LAK": "Laosian Kip",
  "LBP": "Liibanoni nael",
  "LKR": "Sri Lanka ruupia",
  "LRD": "Libeeria dollar",
  "LSL": "Lesotho Loti",
  "LTL": "Leedu litt",
  "LVL": "Läti latid",
  "LYD": "Liibüa dinaar",
  "MAD": "Maroko dirham",
  "MDL": "Moldova leu",
  "MGA": "Madagaskari ariary",
  "MKD": "Makedoonia Denar",
  "MMK": "Myanma Kyat",
  "MNT": "Mongoli Tugrik",
  "MOP": "Aomeni Pataca",
  "MRO": "Mauritaania Ouguiya",
  "MUR": "Mauritiuse ruupia",
  "MVR": "Maldiivi ruufia",
  "MWK": "Malawi Kwacha",
  "MXN": "Mehhiko peeso",
  "MYR": "Malaisia ​​ringgit",
  "MZN": "Mosambiigi Metical",
  "NAD": "Namiibia dollar",
  "NGN": "Nigeeria Naira",
  "NIO": "Nicaragua Córdoba",
  "NOK": "Norra kroon",
  "NPR": "Nepali ruupia",
  "NZD": "Uus-Meremaa dollar",
  "OMR": "Omaani riaal",
  "PAB": "Panama Balboa",
  "PEN": "Peruu Nuevo Sol",
  "PGK": "Paapua Uus-Guinea Kina",
  "PHP": "Filipiinide peeso",
  "PKR": "Pakistani ruupia",
  "PLN": "Poola zlott",
  "PYG": "Paraguay garantiid",
  "QAR": "Katari riaal",
  "RON": "Rumeenia leu",
  "RSD": "Serbia dinaar",
  "RUB": "Vene rubla",
  "RWF": "Rwanda frank",
  "SAR": "Saudi kuninglik",
  "SBD": "Saalomoni Saarte dollar",
  "SCR": "Seišellide ruupia",
  "SDG": "Sudaani nael",
  "SEK": "Rootsi kroon",
  "SGD": "Singapuri dollar",
  "SHP": "Püha Helena nael",
  "SLL": "Sierra Leonean Leone",
  "SOS": "Somaalia šilling",
  "SRD": "Suriname dollar",
  "SSP": "South Sudanese Pound",
  "STD": "São Tomé ja Príncipe Dobra",
  "SVC": "Salvadoran Colón",
  "SYP": "Süüria nael",
  "SZL": "Svaaside Lilangeni",
  "THB": "Tai baht",
  "TJS": "Tadžikistani Somoni",
  "TMT": "Türkmenistani manat",
  "TND": "Tuneesia dinaar",
  "TOP": "Tonga Paʻanga",
  "TRY": "Türgi liir",
  "TTD": "Trinidadi ja Tobago dollar",
  "TWD": "Uus Taiwani dollar",
  "TZS": "Tansaania šilling",
  "UAH": "Ukraina grivna",
  "UGX": "Uganda šilling",
  "USD": "Ameerika Ühendriikide dollar",
  "UYU": "Uruguay peeso",
  "UZS": "Usbekistan Som",
  "VEF": "Venezuela Bolívar Fuerte",
  "VND": "Vietnami dong",
  "VUV": "Vanuatu Vatu",
  "WST": "Samoa Tala",
  "XAF": "CFA Franc BEAC",
  "XAG": "Hõbe (trooja unts)",
  "XAU": "Kuld (trooja unts)",
  "XCD": "Ida-Kariibi dollar",
  "XDR": "Spetsiaalne laenuõigus",
  "XOF": "CFA Franc BCEAO",
  "XPF": "CFP frank",
  "YER": "Jeemeni riaal",
  "ZAR": "Lõuna-Aafrika rand",
  "ZMK": "Sambia Kwacha (2013. aasta eel)",
  "ZMW": "Sambia Kwacha",
  "ZWL": "Zimbabwe dollar",
  "Add Currency": "Lisage valuuta",
  "Selected": "Valitud",
  "Currency List": "Valuutade nimekiri",
  "Rate the app": "Hinnake rakendust",
  "Tap a start to rate it on the Google Play Store": "Selle hindamiseks Google Play poes puudutage alustamist",
  "Terms & Conditions": "Tingimused",
  "Privacy Policy": "Privaatsuspoliitika",
  "Color Selection": "Värvivalik",
  "Select the gradient": "Valige gradient",
  "Visual Size": "Visuaalne suurus",
  "Small": "Väike",
  "Medium": "Keskmine",
  "Large": "Suur",
  "Display": "Kuva",
  "Display Currency Name": "Kuva valuuta nimi",
  "Display Currency Code": "Kuva valuuta nimi",
  "Display Currency Symbol": "Kuva valuutasümbol",
  "Display Currency Flags": "Kuva valuuta lipud",
  "Powered by": "Powered by:",
  "Monetary format": "Rahaline vorming",
  "Decimal format": "Komavorming",
  "Please Rate Us ,)": "Palun hinnake meid :)",
  "Send Money": "Saada raha",
  "Don't show": "Ära näita",
  "Search": "Otsing",
  "Rate Title" : "Ära unusta meid hinnata!",
  "Rate description" : "See võtab vaid paar minutit. Teie väärtuslik tagasiside aitab meil laiendamist täiustada.",
  "Rate button1" : "Hinda kohe",
  "Rate button2" : "Mitte nüüd, võib-olla hiljem",
  "Search/Select Currency": "Otsige / valige valuuta",
  "Date Format": "Kuupäevavorming",
  "Not now": "Mitte praegu"
}
